{
  "_buildCommand2" : {
    "command" : "build",
    "skipDependencies" : false,
    "style" : "buildOnly"
  },
  "buildCommand" : "build",
  "configuredTargets" : [
    {
      "guid" : "PACKAGE-PRODUCT:PackageD"
    },
    {
      "guid" : "PACKAGE-PRODUCT:PackageDTests"
    }
  ],
  "containerPath" : "/Users/fkaanoz/Desktop/dev/PackageD",
  "continueBuildingAfterErrors" : false,
  "enableIndexBuildArena" : false,
  "hideShellScriptEnvironment" : false,
  "parameters" : {
    "action" : "build",
    "activeArchitecture" : "x86_64",
    "activeRunDestination" : {
      "disableOnlyActiveArch" : false,
      "platform" : "macosx",
      "sdk" : "macosx12.3",
      "sdkVariant" : "macos",
      "supportedArchitectures" : [
        "x86_64h",
        "x86_64"
      ],
      "targetArchitecture" : "x86_64"
    },
    "arenaInfo" : {
      "buildIntermediatesPath" : "/Users/fkaanoz/Desktop/dev/PackageD/Build/PackageD-awblwmdxwfpuqzgveavyptzwamap/Build/Intermediates.noindex",
      "buildProductsPath" : "/Users/fkaanoz/Desktop/dev/PackageD/Build/PackageD-awblwmdxwfpuqzgveavyptzwamap/Build/Products",
      "derivedDataPath" : "/Users/fkaanoz/Desktop/dev/PackageD/Build",
      "indexDataStoreFolderPath" : "/Users/fkaanoz/Desktop/dev/PackageD/Build/PackageD-awblwmdxwfpuqzgveavyptzwamap/Index/DataStore",
      "indexEnableDataStore" : true,
      "indexPCHPath" : "/Users/fkaanoz/Desktop/dev/PackageD/Build/PackageD-awblwmdxwfpuqzgveavyptzwamap/Index/PrecompiledHeaders",
      "pchPath" : "/Users/fkaanoz/Desktop/dev/PackageD/Build/PackageD-awblwmdxwfpuqzgveavyptzwamap/Build/Intermediates.noindex/PrecompiledHeaders"
    },
    "configurationName" : "Debug",
    "overrides" : {
      "synthesized" : {
        "table" : {
          "ENABLE_PREVIEWS" : "NO"
        }
      }
    }
  },
  "schemeCommand" : "launch",
  "schemeCommand2" : "launch",
  "shouldCollectMetrics" : false,
  "showNonLoggedProgress" : true,
  "useDryRun" : false,
  "useImplicitDependencies" : true,
  "useLegacyBuildLocations" : false,
  "useParallelTargets" : true
}